daidai/__init__.py
daidai/artifacts.py
daidai/cli.py
daidai/config.py
daidai/decorators.py
daidai/logs.py
daidai/managers.py
daidai/types.py
daidai/py.typed
daidai-0.0.7.dist-info/METADATA
daidai-0.0.7.dist-info/WHEEL
daidai-0.0.7.dist-info/entry_points.txt
daidai-0.0.7.dist-info/licenses/LICENSE
daidai-0.0.7.dist-info/RECORD
